puzzlepy/subset.py
puzzlepy/grid.py
puzzlepy/partition.py
puzzlepy/coord.py
puzzlepy/__init__.py
puzzlepy/skyscrapers.py
puzzlepy/cell.py
puzzlepy/timeout.py
puzzlepy/sudoku.py
puzzlepy-0.1.2.data/scripts/sudoku
puzzlepy-0.1.2.dist-info/DESCRIPTION.rst
puzzlepy-0.1.2.dist-info/WHEEL
puzzlepy-0.1.2.dist-info/metadata.json
puzzlepy-0.1.2.dist-info/METADATA
puzzlepy-0.1.2.dist-info/top_level.txt
puzzlepy-0.1.2.dist-info/RECORD
