Metadata-Version: 2.0
Name: puzzlepy
Version: 0.1.2
Summary: Python package for generating, solving, and testing grid-based puzzle games.
Home-page: https://github.com/basvandenberg/puzzlepy
Author: B.A. van den Berg
Author-email: b.a.vandenberg@gmail.com
License: MIT
Download-URL: https://github.com/basvandenberg/puzzlepy/releases
Platform: UNKNOWN
Classifier: Development Status :: 1 - Planning
Classifier: Environment :: Console
Classifier: Intended Audience :: Developers
Classifier: License :: OSI Approved :: MIT License
Classifier: Natural Language :: English
Classifier: Operating System :: OS Independent
Classifier: Programming Language :: Python :: 3 :: Only
Classifier: Topic :: Games/Entertainment :: Puzzle Games
Classifier: Topic :: Software Development :: Libraries :: Python Modules
